spectramap/__init__.py
spectramap/spmap.py
spectramap-0.5.3.dist-info/LICENSE
spectramap-0.5.3.dist-info/METADATA
spectramap-0.5.3.dist-info/WHEEL
spectramap-0.5.3.dist-info/top_level.txt
spectramap-0.5.3.dist-info/RECORD
