Metadata-Version: 2.1
Name: spectramap
Version: 0.5.3
Summary: Hyperspectral package for spectroscopists
Home-page: https://github.com/spectramap/spectramap
Author: Juan David Muñoz-Bolaños
Author-email: jmunozbolanos@gmail.com
Project-URL: Bug Tracker, https://github.com/spectramap/spectramap
Classifier: Programming Language :: Python :: 3
Classifier: License :: OSI Approved :: MIT License
Classifier: Operating System :: OS Independent
Classifier: Intended Audience :: Science/Research
Classifier: Development Status :: 3 - Alpha
Classifier: Topic :: Software Development :: Bug Tracking
Requires-Python: >=3.6
License-File: LICENSE
Requires-Dist: scikit-learn
Requires-Dist: pyspectra
Requires-Dist: scipy
